WuaiPojieLuntanjinghuaJi2019DisiBufen/README.md
WuaiPojieLuntanjinghuaJi2019DisiBufen/__init__.py
WuaiPojieLuntanjinghuaJi2019DisiBufen/__main__.py
WuaiPojieLuntanjinghuaJi2019DisiBufen/file.epub
WuaiPojieLuntanjinghuaJi2019DisiBufen/index.html
WuaiPojieLuntanjinghuaJi2019DisiBufen/css/__init__.py
WuaiPojieLuntanjinghuaJi2019DisiBufen/css/annotations.css
WuaiPojieLuntanjinghuaJi2019DisiBufen/css/main.css
WuaiPojieLuntanjinghuaJi2019DisiBufen/css/normalize.css
WuaiPojieLuntanjinghuaJi2019DisiBufen/css/popup.css
WuaiPojieLuntanjinghuaJi2019DisiBufen/font/__init__.py
WuaiPojieLuntanjinghuaJi2019DisiBufen/font/fontello.eot
WuaiPojieLuntanjinghuaJi2019DisiBufen/font/fontello.svg
WuaiPojieLuntanjinghuaJi2019DisiBufen/font/fontello.ttf
WuaiPojieLuntanjinghuaJi2019DisiBufen/font/fontello.woff
WuaiPojieLuntanjinghuaJi2019DisiBufen/img/__init__.py
WuaiPojieLuntanjinghuaJi2019DisiBufen/img/annotator-glyph-sprite.png
WuaiPojieLuntanjinghuaJi2019DisiBufen/img/annotator-icon-sprite.png
WuaiPojieLuntanjinghuaJi2019DisiBufen/img/apple-touch-icon.png
WuaiPojieLuntanjinghuaJi2019DisiBufen/img/cancelfullscreen.png
WuaiPojieLuntanjinghuaJi2019DisiBufen/img/close.png
WuaiPojieLuntanjinghuaJi2019DisiBufen/img/fullscreen.png
WuaiPojieLuntanjinghuaJi2019DisiBufen/img/loader.gif
WuaiPojieLuntanjinghuaJi2019DisiBufen/img/menu-icon.png
WuaiPojieLuntanjinghuaJi2019DisiBufen/img/save.png
WuaiPojieLuntanjinghuaJi2019DisiBufen/img/saved.png
WuaiPojieLuntanjinghuaJi2019DisiBufen/img/settings-s.png
WuaiPojieLuntanjinghuaJi2019DisiBufen/img/settings.png
WuaiPojieLuntanjinghuaJi2019DisiBufen/img/star.png
WuaiPojieLuntanjinghuaJi2019DisiBufen/js/__init__.py
WuaiPojieLuntanjinghuaJi2019DisiBufen/js/epub.js
WuaiPojieLuntanjinghuaJi2019DisiBufen/js/epub.min.js
WuaiPojieLuntanjinghuaJi2019DisiBufen/js/epub.min.map
WuaiPojieLuntanjinghuaJi2019DisiBufen/js/hooks.min.js
WuaiPojieLuntanjinghuaJi2019DisiBufen/js/hooks.min.map
WuaiPojieLuntanjinghuaJi2019DisiBufen/js/reader.js
wuai_pojie_luntanjinghua_ji_2019_disi_bufen-2024.3.5.0.dist-info/METADATA
wuai_pojie_luntanjinghua_ji_2019_disi_bufen-2024.3.5.0.dist-info/WHEEL
wuai_pojie_luntanjinghua_ji_2019_disi_bufen-2024.3.5.0.dist-info/entry_points.txt
wuai_pojie_luntanjinghua_ji_2019_disi_bufen-2024.3.5.0.dist-info/top_level.txt
wuai_pojie_luntanjinghua_ji_2019_disi_bufen-2024.3.5.0.dist-info/RECORD
